{"pageProps":{"episode":{"id":"1713369600000","title":"Cracking the Code: Pen Testing and the Cybertruck Conundrum","description":"<p>  We delve into the realm of cybersecurity through the lens of penetration testing, a critical and intriguing field that addresses the security vulnerabilities of computer systems by simulating cyberattacks. Penetration testing, often referred to as \"pen testing,\" involves skilled professionals known as penetration testers or ethical hackers, who use their expertise in hacking tools and techniques not to cause harm, but to identify and rectify security weaknesses. Companies engage these specialists to perform simulated attacks on their networks, applications, and other digital assets, enabling them to discover and mitigate potential security risks effectively. This practice not only helps in safeguarding against actual cyber threats but also significantly enhances a company's overall security posture. Additionally, the podcast will touch on the broader field of ethical hacking, which encompasses various services beyond penetration testing, such as malware analysis and risk assessment, highlighting the essential role these activities play in strengthening network security.</p><p>  We also explore the significant consumer dissatisfaction surrounding Tesla's Cybertruck. Owners have reported a range of issues from basic operational failures like the vehicle not turning on or charging, to more alarming concerns about visibility problems that pose safety risks. Critics, including those found on platforms such as Jalopnik, point to rushed production and cost-cutting measures as potential causes for these defects. The complaints have been so severe that some have been removed from forums only to resurface elsewhere due to their critical nature. </p><p></p>","published":1713369600000,"audio":{"src":"https://media.blubrry.com/1473047/ins.blubrry.com/1473047/twr20240417.mp3","type":"audio/mpeg"}}},"__N_SSG":true}