{"pageProps":{"episode":{"id":"1718467200000","title":"AI Revolution in Music & Sam's Alarm Clock Idea","description":"<p>In this exciting episode, we dive into the revolutionary impact of artificial intelligence on music creation. Discover how AI is transforming the music industry, from composing underscores to generating hit songs. Later in the episode, join us for a hilarious and innovative brainstorming session as Sam unveils his quirky new idea on an Alarm clock with a surprise!</p>","published":1718467200000,"audio":{"src":"https://media.blubrry.com/1473047/ins.blubrry.com/1473047/twr20240615.mp3","type":"audio/mpeg"}}},"__N_SSG":true}